mcp_daily_news/__init__.py
mcp_daily_news/__main__.py
mcp_daily_news/main.py
mcp_daily_news/types.py
mcp_daily_news/tools/9to5mac.py
mcp_daily_news/tools/__init__.py
mcp_daily_news/tools/autohome.py
mcp_daily_news/tools/baidu.py
mcp_daily_news/tools/bbc.py
mcp_daily_news/tools/bilibili.py
mcp_daily_news/tools/custom_rss.py
mcp_daily_news/tools/douban.py
mcp_daily_news/tools/douyin.py
mcp_daily_news/tools/gcores.py
mcp_daily_news/tools/hupu.py
mcp_daily_news/tools/ifanr.py
mcp_daily_news/tools/infoq.py
mcp_daily_news/tools/ithome.py
mcp_daily_news/tools/kr36.py
mcp_daily_news/tools/kuaishou.py
mcp_daily_news/tools/netease_news.py
mcp_daily_news/tools/nytimes.py
mcp_daily_news/tools/smzdm.py
mcp_daily_news/tools/so360.py
mcp_daily_news/tools/sogou.py
mcp_daily_news/tools/sspai.py
mcp_daily_news/tools/tencent_news.py
mcp_daily_news/tools/thepaper.py
mcp_daily_news/tools/theverge.py
mcp_daily_news/tools/tieba.py
mcp_daily_news/tools/toutiao.py
mcp_daily_news/tools/weibo.py
mcp_daily_news/tools/weread.py
mcp_daily_news/tools/xiaohongshu.py
mcp_daily_news/tools/xueqiu.py
mcp_daily_news/tools/zhihu.py
mcp_daily_news/utils/__init__.py
mcp_daily_news/utils/cache.py
mcp_daily_news/utils/helpers.py
mcp_daily_news/utils/http.py
mcp_daily_news/utils/logger.py
mcp_daily_news/utils/rss.py
mcp_daily_news-1.6.3.dist-info/METADATA
mcp_daily_news-1.6.3.dist-info/WHEEL
mcp_daily_news-1.6.3.dist-info/entry_points.txt
mcp_daily_news-1.6.3.dist-info/top_level.txt
mcp_daily_news-1.6.3.dist-info/RECORD
