Metadata-Version: 2.4
Name: mcp_daily_news
Version: 1.6.3
Summary: 🔥 基于 Model Context Protocol (MCP) 协议的全网热点趋势一站式聚合服务
Author: sunjackson
License-Expression: MIT
Project-URL: Homepage, https://github.com/sunjackson/mcp_daily_news
Project-URL: Repository, https://github.com/sunjackson/mcp_daily_news.git
Project-URL: Issues, https://github.com/sunjackson/mcp_daily_news/issues
Keywords: mcp,daily,news
Classifier: Programming Language :: Python :: 3
Classifier: Operating System :: OS Independent
Requires-Python: >=3.10
Requires-Dist: mcp>=1.7.0
Requires-Dist: httpx>=0.25.0
Requires-Dist: pydantic>=2.0.0
Requires-Dist: lxml>=4.9.0
Requires-Dist: python-dateutil>=2.8.0
Requires-Dist: feedparser>=6.0.0
Provides-Extra: dev
Requires-Dist: pytest>=7.0.0; extra == "dev"
Requires-Dist: pytest-asyncio>=0.21.0; extra == "dev"
Requires-Dist: black>=23.0.0; extra == "dev"
Requires-Dist: isort>=5.12.0; extra == "dev"
Requires-Dist: mypy>=1.0.0; extra == "dev"
Requires-Dist: pre-commit>=3.0.0; extra == "dev"
